zayt-0.1.0.dist-info/METADATA
zayt-0.1.0.dist-info/WHEEL
zayt-0.1.0.dist-info/entry_points.txt
zayt-0.1.0.dist-info/licenses/LICENSE
zayt/__init__.py
zayt/__version__.py
zayt/conf/__init__.py
zayt/conf/defaults.py
zayt/conf/environment.py
zayt/conf/settings.py
zayt/di/__init__.py
zayt/di/call.py
zayt/di/container.py
zayt/di/decorator.py
zayt/di/error.py
zayt/di/inject.py
zayt/di/interceptor.py
zayt/di/service/__init__.py
zayt/di/service/model.py
zayt/di/service/parse.py
zayt/di/service/registry.py
zayt/ext/__init__.py
zayt/ext/error.py
zayt/ext/jinja/__init__.py
zayt/ext/jinja/service.py
zayt/ext/memcached/__init__.py
zayt/ext/memcached/service.py
zayt/ext/redis/__init__.py
zayt/ext/redis/service.py
zayt/ext/sqlalchemy/__init__.py
zayt/ext/sqlalchemy/service.py
zayt/logging.py
zayt/py.typed
zayt/run.py
zayt/util/__init__.py
zayt/util/asgi.py
zayt/util/base_types.py
zayt/util/dotenv.py
zayt/util/import_item.py
zayt/util/maybe_async.py
zayt/util/package_scan.py
zayt/web/__init__.py
zayt/web/application.py
zayt/web/exception.py
zayt/web/exception_handler/__init__.py
zayt/web/exception_handler/decorator.py
zayt/web/exception_handler/discover.py
zayt/web/handler/__init__.py
zayt/web/handler/model.py
zayt/web/handler/parse.py
zayt/web/lifecycle/__init__.py
zayt/web/lifecycle/decorator.py
zayt/web/lifecycle/discover.py
zayt/web/middleware/__init__.py
zayt/web/middleware/files.py
zayt/web/middleware/request_id.py
zayt/web/routing/__init__.py
zayt/web/routing/decorator.py
zayt/web/routing/exception.py
zayt/web/routing/route.py
zayt/web/routing/router.py
zayt-0.1.0.dist-info/RECORD
